jengahq/__init__.py
jengahq/auth.py
jengahq/exceptions.py
jengahq/helpers.py
jengahq/receive_money.py
jengahq/send_money.py
jengahq/receive_money/LNMOnline.py
jengahq/receive_money/__init__.py
jengahq/receive_money/bill_payments.py
jengahq/receive_money/bill_validation.py
jengahq/receive_money/eazzypay_push.py
jengahq/receive_money/merchant_payments.py
jengahq/receive_money/queries.py
jengahq/receive_money/refund_payments.py
pyjengahq-0.1.2.dist-info/LICENSE
pyjengahq-0.1.2.dist-info/METADATA
pyjengahq-0.1.2.dist-info/WHEEL
pyjengahq-0.1.2.dist-info/entry_points.txt
pyjengahq-0.1.2.dist-info/pbr.json
pyjengahq-0.1.2.dist-info/top_level.txt
pyjengahq-0.1.2.dist-info/RECORD
